{
    "authRoutes":[
        {
            "path":"/login",
            "name":"Login"
        }
    ],
    "dashboardRoutes":{
        "Dashboard":{
            "path":"/",
            "name":"Dashboard",
            "logo":"Speedometer2"
        },
        "Payments":{
            "path":"/payments",
            "name":"Payments",
            "logo":"Wallet"
        },
        "Dues":{
            "path":"/Dues",
            "name":"Dues",
            "logo":"CreditCard"
        },
        "Add Accounts":{
            "path":"/add",
            "name":"Add Accounts",
            "logo":"PlusCircle"
        },
        "Teachers":{
            "path":"/teachers",
            "name":"Teachers",
            "logo":"PersonCircle"
        },
        "Students":{
            "path":"/students",
            "name":"Students",
            "logo":"PersonCircle"
        }

    }
}